pyjen/__init__.py
pyjen/build.py
pyjen/changeset.py
pyjen/jenkins.py
pyjen/job.py
pyjen/node.py
pyjen/plugin.py
pyjen/plugin_manager.py
pyjen/queue.py
pyjen/queue_item.py
pyjen/user.py
pyjen/version.py
pyjen/view.py
pyjen/plugins/__init__.py
pyjen/plugins/allview.py
pyjen/plugins/artifactarchiver.py
pyjen/plugins/artifactdeployer.py
pyjen/plugins/buildblocker.py
pyjen/plugins/buildtriggerpublisher.py
pyjen/plugins/conditionalbuilder.py
pyjen/plugins/flexiblepublish.py
pyjen/plugins/folderjob.py
pyjen/plugins/freestylejob.py
pyjen/plugins/gitscm.py
pyjen/plugins/listview.py
pyjen/plugins/mavenplugin.py
pyjen/plugins/multibranch_pipeline.py
pyjen/plugins/multijob.py
pyjen/plugins/myview.py
pyjen/plugins/nestedview.py
pyjen/plugins/nullscm.py
pyjen/plugins/parambuild_string.py
pyjen/plugins/parameterizedbuild.py
pyjen/plugins/paramtrigger.py
pyjen/plugins/paramtrigger_buildtrigger.py
pyjen/plugins/paramtrigger_currentbuildparams.py
pyjen/plugins/pipelinejob.py
pyjen/plugins/runcondition_always.py
pyjen/plugins/runcondition_and.py
pyjen/plugins/runcondition_never.py
pyjen/plugins/runcondition_not.py
pyjen/plugins/sectionedview.py
pyjen/plugins/sectionedview_listsection.py
pyjen/plugins/sectionedview_textsection.py
pyjen/plugins/shellbuilder.py
pyjen/plugins/statusview.py
pyjen/plugins/subversion.py
pyjen/utils/__init__.py
pyjen/utils/helpers.py
pyjen/utils/jenkins_api.py
pyjen/utils/jobxml.py
pyjen/utils/plugin_api.py
pyjen/utils/viewxml.py
pyjen/utils/xml_plugin.py
pyjen-1.1.0.dist-info/LICENSE
pyjen-1.1.0.dist-info/METADATA
pyjen-1.1.0.dist-info/WHEEL
pyjen-1.1.0.dist-info/entry_points.txt
pyjen-1.1.0.dist-info/top_level.txt
pyjen-1.1.0.dist-info/RECORD
