Metadata-Version: 2.1
Name: pyjen
Version: 1.1.0
Summary: Python wrapper for the Jenkins CI REST API
Home-page: https://github.com/TheFriendlyCoder/pyjen
Author: Kevin S. Phillips
Author-email: thefriendlycoder@gmail.com
License: Apache License 2.0
Keywords: jenkins jenkins-ci api wrapper library
Platform: UNKNOWN
Classifier: Development Status :: 3 - Alpha
Classifier: Environment :: Console
Classifier: License :: OSI Approved :: Apache Software License
Classifier: Topic :: Software Development :: Libraries
Classifier: Natural Language :: English
Classifier: Operating System :: OS Independent
Classifier: Programming Language :: Python :: 2
Classifier: Programming Language :: Python :: 3
Requires-Python: >=2.7, !=3.0.*, !=3.1.*, !=3.2.*, !=3.3.*
Requires-Dist: requests
Requires-Dist: six
Requires-Dist: tqdm
Provides-Extra: dev
Requires-Dist: pytest ; extra == 'dev'
Requires-Dist: pytest-timeout ; extra == 'dev'
Requires-Dist: mock ; extra == 'dev'
Requires-Dist: pylint ; extra == 'dev'
Requires-Dist: tox ; extra == 'dev'
Requires-Dist: tox-factor ; extra == 'dev'
Requires-Dist: docker ; extra == 'dev'
